{
  "brand": null,
  "camera": "652759",
  "color": null,
  "confidence": 85.4902,
  "federal_vehicle_information": [],
  "finish": 1690037609000,
  "id": 768310333,
  "image_url": "https://objectstorage.sa-saopaulo-1.oraclecloud.com/n/grtqyv6nwfc2/b/intelbras/o/6a5c3120-3d9d-11ed-9816-79eff64c2d45.stream/MHS2I99-20230722115327.jpg",
  "model": null,
  "plate": "MHS2I99",
  "plate_position": "[{\"x\": 1093, \"y\": 441}, {\"x\": 1093, \"y\": 475}, {\"x\": 1194, \"y\": 475}, {\"x\": 1194, \"y\": 441}]",
  "registry": null,
  "start": 1690037609000,
  "type": null,
  "vehicle_information": [],
  "vehicle_position": null,
  "carbigdata_vehicle_information": {
      "brand": "FIAT",
      "brand_model": "I/FIAT SIENA EL FLEX",
      "city": "",
      "color": "Preta",
      "model": "SIENA",
      "model_year": "2011",
      "plate": "MHS2I99",
      "registry": null,
      "type": "Automovel",
      "vehicle_esp_cod": "153019"
  },
  "is_blacklist": false,
  "blacklist_infos": [],
  "Camera.cameraId": 652759,
  "Camera.title": "Av. Santos Dumont nยบ 935 - Joinville",
  "Camera.timezone": "America/Bahia",
  "dateTZFormatted": "22/07/2023 11:53"
}
